jaxgb/__init__.py
jaxgb/py.typed
jaxgb-0.1.0.dist-info/METADATA
jaxgb-0.1.0.dist-info/WHEEL
jaxgb-0.1.0.dist-info/licenses/LICENSE
jaxgb-0.1.0.dist-info/RECORD
