Metadata-Version: 2.4
Name: jaxgb
Version: 0.1.0
Summary: Fast LISA response for Galactic binaries using JAX
Author-email: Jean-Baptiste Bayle <j2b.bayle@gmail.com>, Maude Le Jeune <lejeune@apc.in2p3.fr>
License: BSD-3-Clause
License-File: LICENSE
Keywords: GW,LISA,gravitational wave,waveform
Classifier: Intended Audience :: Science/Research
Classifier: Topic :: Scientific/Engineering :: Astronomy
Classifier: Topic :: Scientific/Engineering :: Physics
Requires-Python: >=3.12
Requires-Dist: jax>=0.7.2
Requires-Dist: lisaconstants>=1.3.6
Requires-Dist: lisaorbits>=2.4.2
Requires-Dist: numpy>=2.3.3
